relativity/__init__.py
relativity/compat.py
relativity/fields.py
relativity/mptt.py
relativity/treebeard.py
django_relativity-0.2.6.dist-info/LICENSE
django_relativity-0.2.6.dist-info/METADATA
django_relativity-0.2.6.dist-info/WHEEL
django_relativity-0.2.6.dist-info/top_level.txt
django_relativity-0.2.6.dist-info/RECORD
