Metadata-Version: 2.1
Name: django-relativity
Version: 0.2.6
Summary: A flexible relationship field for the Django ORM.
Home-page: https://github.com/alexhill/django-relativity
Author: Alex Hill
Author-email: alex@hill.net.au
Classifier: Development Status :: 4 - Beta
Classifier: Environment :: Web Environment
Classifier: Framework :: Django
Classifier: Intended Audience :: Developers
Classifier: License :: OSI Approved :: BSD License
Classifier: Natural Language :: English
Classifier: Operating System :: OS Independent
Classifier: Programming Language :: Python :: 2.7
Classifier: Programming Language :: Python :: 3
License-File: LICENSE
Requires-Dist: django (>=1.11)
